coverage_shield/__init__.py
coverage_shield/__main__.py
coverage_shield/badges.py
coverage_shield/slug.py
coverage_shield-1.0.8.dist-info/LICENSE
coverage_shield-1.0.8.dist-info/METADATA
coverage_shield-1.0.8.dist-info/WHEEL
coverage_shield-1.0.8.dist-info/top_level.txt
coverage_shield-1.0.8.dist-info/RECORD
