Metadata-Version: 2.1
Name: coverage-shield
Version: 1.0.8
Summary: Uploads total coverage for displaying badge
Home-page: https://github.com/Volumental/badges
Author: Samuel Carlsson
Author-email: samuel.carlsson@volumental.com
License: UNKNOWN
Keywords: coverage,badge,shields.io
Platform: UNKNOWN
Requires-Dist: coverage
